import_x/__init__.py
import_x/loaders/__init__.py
import_x/loaders/json_loader.py
import_x-0.1.1.dist-info/LICENSE
import_x-0.1.1.dist-info/WHEEL
import_x-0.1.1.dist-info/METADATA
import_x-0.1.1.dist-info/RECORD
