Metadata-Version: 2.1
Name: import-x
Version: 0.1.1
Summary: Import non-python files
Home-page: https://github.com/deepsourcelabs/import-x
License: MIT
Keywords: import machinary,import hook,import-x
Author: Mohit Solanki
Author-email: mohit@deepsource.io
Requires-Python: >=3.6,<4.0
Classifier: License :: OSI Approved :: MIT License
Classifier: Programming Language :: Python :: 3
Classifier: Programming Language :: Python :: 3.6
Classifier: Programming Language :: Python :: 3.7
Classifier: Topic :: Software Development :: Libraries :: Python Modules
Project-URL: Documentation, https://github.com/deepsourcelabs/import-x
Project-URL: Repository, https://github.com/deepsourcelabs/import-x
